MANIFEST.in
README
setup.py
django_ikari.egg-info/PKG-INFO
django_ikari.egg-info/SOURCES.txt
django_ikari.egg-info/dependency_links.txt
django_ikari.egg-info/requires.txt
django_ikari.egg-info/top_level.txt
ikari/__init__.py
ikari/__init__.pyc
ikari/admin.py
ikari/admin.pyc
ikari/cache.py
ikari/cache.pyc
ikari/decorators.pyc
ikari/error_urls.py
ikari/error_urls.pyc
ikari/fields.py
ikari/forms.py
ikari/middleware.py
ikari/middleware.pyc
ikari/mixins.py
ikari/models.py
ikari/models.pyc
ikari/settings.py
ikari/settings.pyc
ikari/signals.py
ikari/signals.pyc
ikari/views.py
ikari/views.pyc