Metadata-Version: 1.0
Name: django-ikari
Version: 0.0.5
Summary: Django middleware to allow user configurable domain anchoring to admin configured urlconfs.
Home-page: UNKNOWN
Author: Zenobius Jiricek
Author-email: airtonix@gmail.com
License: UNKNOWN
Platform: UNKNOWN
